assemblyai_tool/__init__.py
assemblyai_tool-0.2.1.dist-info/METADATA
assemblyai_tool-0.2.1.dist-info/WHEEL
assemblyai_tool-0.2.1.dist-info/entry_points.txt
assemblyai_tool-0.2.1.dist-info/licenses/LICENSE
assemblyai_tool-0.2.1.dist-info/RECORD
