Metadata-Version: 2.4
Name: assemblyai-tool
Version: 0.2.1
Summary: Simple CLI wrapper around the AssemblyAI Python SDK
Author-email: Yaniv Aknin <yaniv@aknin.name>
License-File: LICENSE
Requires-Python: >=3.12
Requires-Dist: assemblyai>=0.36.0
Requires-Dist: python-dotenv>=1.0.1
Requires-Dist: typer>=0.15.1
